docubot/__init__.py
docubot/docubot.py
docubot-0.1.9.dist-info/LICENSE
docubot-0.1.9.dist-info/METADATA
docubot-0.1.9.dist-info/WHEEL
docubot-0.1.9.dist-info/entry_points.txt
docubot-0.1.9.dist-info/RECORD
